openedx_atlas/__ini__.py
openedx_atlas-0.7.0.data/scripts/atlas
openedx_atlas-0.7.0.dist-info/LICENSE
openedx_atlas-0.7.0.dist-info/METADATA
openedx_atlas-0.7.0.dist-info/WHEEL
openedx_atlas-0.7.0.dist-info/top_level.txt
openedx_atlas-0.7.0.dist-info/RECORD
