Metadata-Version: 2.1
Name: openedx-atlas
Version: 0.7.0
Summary: An Open edX CLI tool for moving translation files from openedx-translations.
Home-page: https://github.com/openedx/openedx-atlas
Author: Open edX project
Author-email: oscm@axim.org
License: AGPL 3.0
Classifier: Intended Audience :: Developers
Classifier: License :: OSI Approved :: GNU Affero General Public License v3 or later (AGPLv3+)
Classifier: Natural Language :: English
License-File: LICENSE
